CHANGES.rst
MANIFEST.in
README.rst
setup.py
.tx/config
docs/INSTALL.rst
docs/LICENSE.GPL
docs/LICENSE.rst
src/collective/__init__.py
src/collective.folderishtypes.egg-info/PKG-INFO
src/collective.folderishtypes.egg-info/SOURCES.txt
src/collective.folderishtypes.egg-info/dependency_links.txt
src/collective.folderishtypes.egg-info/entry_points.txt
src/collective.folderishtypes.egg-info/namespace_packages.txt
src/collective.folderishtypes.egg-info/not-zip-safe
src/collective.folderishtypes.egg-info/requires.txt
src/collective.folderishtypes.egg-info/top_level.txt
src/collective/folderishtypes/__init__.py
src/collective/folderishtypes/caching.zcml
src/collective/folderishtypes/configure.zcml
src/collective/folderishtypes/interfaces.py
src/collective/folderishtypes/profiles.zcml
src/collective/folderishtypes/upgrades.py
src/collective/folderishtypes/upgrades.zcml
src/collective/folderishtypes/vocabularies.py
src/collective/folderishtypes/at/__init__.py
src/collective/folderishtypes/at/configure.zcml
src/collective/folderishtypes/at/content.py
src/collective/folderishtypes/at/interfaces.py
src/collective/folderishtypes/at/permissions.zcml
src/collective/folderishtypes/at/setuphandlers.py
src/collective/folderishtypes/at/upgrades.py
src/collective/folderishtypes/at/upgrades.zcml
src/collective/folderishtypes/at/browser/__init__.py
src/collective/folderishtypes/at/browser/adapters.py
src/collective/folderishtypes/at/browser/configure.zcml
src/collective/folderishtypes/at/browser/folder_listing.pt
src/collective/folderishtypes/at/browser/folder_summary_view.pt
src/collective/folderishtypes/at/browser/folderishtypes.css
src/collective/folderishtypes/at/migration/__init__.py
src/collective/folderishtypes/at/migration/configure.zcml
src/collective/folderishtypes/at/migration/migrate_plonearticle.py
src/collective/folderishtypes/at/profiles/default/browserlayer.xml
src/collective/folderishtypes/at/profiles/default/collective.folderishtypes-default.txt
src/collective/folderishtypes/at/profiles/default/cssregistry.xml
src/collective/folderishtypes/at/profiles/default/diff_tool.xml
src/collective/folderishtypes/at/profiles/default/factorytool.xml
src/collective/folderishtypes/at/profiles/default/import_steps.xml
src/collective/folderishtypes/at/profiles/default/metadata.xml
src/collective/folderishtypes/at/profiles/default/portal_atct.xml
src/collective/folderishtypes/at/profiles/default/propertiestool.xml
