Metadata-Version: 2.1
Name: collective.folderishtypes
Version: 3.1
Summary: Folderish News Item, Document and Event as replacement for default types.
Home-page: http://github.com/collective/collective.folderishtypes
Author: Johannes Raggam
Author-email: johannes@raggam.co.at
License: GPL
Keywords: content types plone folderish
Platform: UNKNOWN
Classifier: Framework :: Plone
Classifier: Framework :: Plone :: 5.1
Classifier: Framework :: Plone :: 5.2
Classifier: Programming Language :: Python
Classifier: Programming Language :: Python :: 2.7
Classifier: Programming Language :: Python :: 3.6
Classifier: Programming Language :: Python :: 3.7
Classifier: License :: OSI Approved :: GNU General Public License (GPL)
Provides-Extra: archetypes
Provides-Extra: dexterity
Provides-Extra: migration
